{
    "backend": "api-server-django",
    "db_name": "",
    "db_pass": "",
    "db_type": "sqlite",
    "db_user": "",
    "dbms": "1",
    "description": "generated product",
    "design": "berry-dashboard",
    "docker": "0",
    "err_code": 0,
    "frontend": "react",
    "heroku": "0",
    "pattern": "fullstack",
    "pro": "0",
    "task_id": "8e3209ca-47e0-4d85-bc1b-91bfd913c10e",
    "task_info": "Upload Sources [0%] - 171 files",
    "task_output": "8e3209ca-47e0-4d85-bc1b-91bfd913c10e.zip",
    "task_result": "SUCCESS",
    "task_state": "RUNNING",
    "task_ts_end": "2025-01-18-22-06-56",
    "task_ts_start": "2025-01-18-22-06-55"
}